topsis/102217020.py
topsis/__init__.py
Topsis_Harshil_102217020-1.0.0.dist-info/LICENSE.txt
Topsis_Harshil_102217020-1.0.0.dist-info/METADATA
Topsis_Harshil_102217020-1.0.0.dist-info/WHEEL
Topsis_Harshil_102217020-1.0.0.dist-info/top_level.txt
Topsis_Harshil_102217020-1.0.0.dist-info/RECORD
